xmind2zantao/__init__.py
xmind2zantao/datatype.py
xmind2zantao/xmind_parser.py
xmind2zantao/zandao_helper.py
xmind2zantao/zentao.py
xmind2zantao_web/__init__.py
xmind2zantao_web/application.py
xmind2zantao_web/schema.sql
xmind2zantao_web/static/favicon.ico
xmind2zantao_web/static/css/head.css
xmind2zantao_web/static/css/login.css
xmind2zantao_web/static/css/pure-min.css
xmind2zantao_web/static/css/style.css
xmind2zantao_web/static/css/v2.css
xmind2zantao_web/static/guide/index.html
xmind2zantao_web/static/guide/index.md
xmind2zantao_web/static/guide/xmind2zantao.xmind
xmind2zantao_web/static/guide/产品ID.png
xmind2zantao_web/static/guide/前置条件.png
xmind2zantao_web/static/guide/测试用例标记.png
xmind2zantao_web/static/guide/用例类型.png
xmind2zantao_web/static/guide/登录.png
xmind2zantao_web/static/guide/禅道模块树展示.png
xmind2zantao_web/static/guide/预览.png
xmind2zantao_web/static/guide/首页.png
xmind2zantao_web/templates/base.html
xmind2zantao_web/templates/index.html
xmind2zantao_web/templates/login.html
xmind2zantao_web/templates/preview.html
xmind2zantao_web/templates/preview_tree.html
xmind2zantao-2.0.2.dist-info/LICENSE
xmind2zantao-2.0.2.dist-info/METADATA
xmind2zantao-2.0.2.dist-info/WHEEL
xmind2zantao-2.0.2.dist-info/top_level.txt
xmind2zantao-2.0.2.dist-info/RECORD
