Metadata-Version: 2.1
Name: xmind2zantao
Version: 2.0.2
Summary: Convert xmind to zantao csv
Home-page: https://github.com/lileixuan/xmind2zantao
Author: LileiXuan
Author-email: lileixuan@gmail.com
License: UNKNOWN
Keywords: xmind zantao import converter testing testcase
Platform: UNKNOWN
Classifier: License :: OSI Approved :: MIT License
Classifier: Topic :: Software Development
Classifier: Topic :: Utilities
Classifier: Operating System :: OS Independent
Classifier: Programming Language :: Python :: 2.7
Requires-Dist: xmindparser
Requires-Dist: requests (<2.28)
Requires-Dist: MarkupSafe (==1.1.1)
Requires-Dist: flask (==1.1.4)
Requires-Dist: arrow (==0.17.0)
Requires-Dist: gunicorn (==19.10.0)
